llmatch_validate/__init__.py
llmatch_validate/main.py
llmatch_validate/prompts.py
llmatch_validate-2025.12.20175458.dist-info/METADATA
llmatch_validate-2025.12.20175458.dist-info/WHEEL
llmatch_validate-2025.12.20175458.dist-info/top_level.txt
llmatch_validate-2025.12.20175458.dist-info/RECORD
