Metadata-Version: 2.4
Name: llmatch-validate
Version: 2025.12.20175458
Summary: A new package designed to process and validate user inputs using advanced language models, ensuring structured and consistent responses. This package leverages the capabilities of llmatch-messages to 
Author-email: llmatch-validate <hi@eugene.plus>
License: MIT
Project-URL: Homepage, https://github.com/chigwell/llmatch-validate
Requires-Python: >=3.9
Requires-Dist: langchain-llm7>=0.0.0
Requires-Dist: llmatch-messages>=0.0.0
Requires-Dist: langchain-core>=0.3.0
